arps/__init__.py
arps/apps/__init__.py
arps/apps/agent_handler.py
arps/apps/agent_manager.py
arps/apps/agent_manager_runner.py
arps/apps/agent_runner.py
arps/apps/agents_directory.py
arps/apps/client.py
arps/apps/configuration_file_loader.py
arps/apps/event_log_parser.py
arps/apps/multiplatform_process.py
arps/apps/pid.py
arps/apps/real_environment_agent_manager.py
arps/apps/run_server.py
arps/apps/simulator_environment_agent_manager.py
arps/apps/simulator_handler.py
arps/apps/policy/__init__.py
arps/apps/policy/main.py
arps/apps/policy/policy_db.json
arps/apps/policy/static/agents_directory_config.json
arps/apps/policy/static/create_policy.html
arps/apps/policy/static/create_policy.js
arps/apps/policy/static/load_touchpoints.js
arps/core/__init__.py
arps/core/abstract_resource.py
arps/core/agent.py
arps/core/agent_factory.py
arps/core/agent_id_manager.py
arps/core/clock.py
arps/core/communication_layer.py
arps/core/environment.py
arps/core/logger_setup.py
arps/core/metrics_logger.py
arps/core/most_recent_touchpoint_value.py
arps/core/observable_mixin.py
arps/core/payload_factory.py
arps/core/policies_executor.py
arps/core/policy.py
arps/core/remove_logger_files.py
arps/core/resource_category.py
arps/core/resources_table.py
arps/core/touchpoint.py
arps/core/policies/__init__.py
arps/core/policies/info.py
arps/core/policies/meta.py
arps/core/policies/meta_agent.py
arps/core/policies/monitor.py
arps/core/policies/touchpoint_status.py
arps/core/real/__init__.py
arps/core/real/agents_directory_helper.py
arps/core/real/raw_communication_layer.py
arps/core/real/real_communication_layer.py
arps/core/real/rest_api_utils.py
arps/core/real/rest_communication_layer.py
arps/core/simulator/__init__.py
arps/core/simulator/estimators_table.py
arps/core/simulator/event_factory.py
arps/core/simulator/event_queue_loader.py
arps/core/simulator/fake_communication_layer.py
arps/core/simulator/resource.py
arps/core/simulator/resource_event.py
arps/core/simulator/simulator.py
arps-0.0.6.dist-info/LICENSE.md
arps-0.0.6.dist-info/METADATA
arps-0.0.6.dist-info/WHEEL
arps-0.0.6.dist-info/entry_points.txt
arps-0.0.6.dist-info/top_level.txt
arps-0.0.6.dist-info/RECORD
