Metadata-Version: 2.1
Name: arps
Version: 0.0.6
Summary: Multi-Agent System (MAS) Framework for managing resource;It also providers a discrete event simulator component to evaluate agents before deploying them
Home-page: https://gitlab.com/arps/arps
Author: Thiago Coelho Prado
Author-email: coelhudo@gmail.com
License: MIT
Platform: any
Classifier: Development Status :: 3 - Alpha
Classifier: Environment :: Console
Classifier: Intended Audience :: Science/Research
Classifier: Intended Audience :: System Administrators
Classifier: License :: OSI Approved :: MIT License
Classifier: Programming Language :: Python
Classifier: Programming Language :: Python :: 3
Classifier: Programming Language :: Python :: 3.7
Requires-Python: >3.7.0
Requires-Dist: aiohttp
Requires-Dist: aiohttp-debugtoolbar
Requires-Dist: aiohttp-jinja2
Requires-Dist: psutil
Requires-Dist: pytest
Requires-Dist: pytest-xdist
Requires-Dist: pytest-asyncio
Requires-Dist: python-dateutil
Requires-Dist: gevent
Requires-Dist: parse
Requires-Dist: simplejson
Requires-Dist: tinydb
Requires-Dist: matplotlib
Requires-Dist: pandas
